setup.py
gbprojectcal/__init__.py
gbprojectcal/gbprojectcal.py
gbprojectcal.egg-info/PKG-INFO
gbprojectcal.egg-info/SOURCES.txt
gbprojectcal.egg-info/dependency_links.txt
gbprojectcal.egg-info/top_level.txt