Metadata-Version: 2.1
Name: gbprojectcal
Version: 0.1
Summary: Calculator
Author: GB
